housing/__init__.py
housing/default_config.conf
housing/ingest_data.py
housing/score.py
housing/train.py
housing-0.3.dist-info/METADATA
housing-0.3.dist-info/WHEEL
housing-0.3.dist-info/licenses/LICENSE.txt
housing-0.3.dist-info/RECORD
